automix/__init__.py
automix/automix_methods.py
automix/main.py
automix_llm-1.0.3.dist-info/LICENSE
automix_llm-1.0.3.dist-info/METADATA
automix_llm-1.0.3.dist-info/WHEEL
automix_llm-1.0.3.dist-info/top_level.txt
automix_llm-1.0.3.dist-info/RECORD
