Metadata-Version: 2.1
Name: automix-llm
Version: 1.0.3
Summary: Library for Mixing Multiple Models with differential costs and performance.
License: Apache License 2.0
License-File: LICENSE
Requires-Dist: numpy
Requires-Dist: pandas
Requires-Dist: scipy
Requires-Dist: tqdm
